worth/__init__.py
worth/_patches.py
worth/py.typed
worth/pytest_plugin.py
worth-0.3.0.dist-info/LICENSE
worth-0.3.0.dist-info/METADATA
worth-0.3.0.dist-info/WHEEL
worth-0.3.0.dist-info/entry_points.txt
worth-0.3.0.dist-info/RECORD
