Metadata-Version: 2.1
Name: worth
Version: 0.3.0
Summary: Assert relevant object attributes
Home-page: https://github.com/johnnoone/worth
License: BSD-3-Clause
Keywords: test,assertion
Author: Xavier Barbosa
Author-email: clint.northwood@gmail.com
Requires-Python: >=3.10,<4.0
Classifier: Development Status :: 3 - Alpha
Classifier: Framework :: Pytest
Classifier: License :: OSI Approved :: BSD License
Classifier: Programming Language :: Python :: 3
Classifier: Programming Language :: Python :: 3.10
Classifier: Programming Language :: Python :: 3.11
Classifier: Programming Language :: Python :: 3.12
Classifier: Topic :: Software Development :: Testing
Classifier: Topic :: Software Development :: Testing :: Mocking
Provides-Extra: attrs
Provides-Extra: msgspec
Requires-Dist: attrs ; extra == "attrs"
Requires-Dist: msgspec ; extra == "msgspec"
Requires-Dist: typing-extensions
Project-URL: Repository, https://github.com/johnnoone/worth
